radiotools/__init__.py
radiotools/coordinatesystems.py
radiotools/helper.py
radiotools/leapseconds.py
radiotools/plthelpers.py
radiotools/stats.py
radiotools/analyses/__init__.py
radiotools/analyses/energy_fluence.py
radiotools/analyses/radiationenergy.py
radiotools/atmosphere/__init__.py
radiotools/atmosphere/models.py
radiotools/atmosphere/refractivity.py
radiotools/coreas/GE.py
radiotools/coreas/LSF.py
radiotools/coreas/__init__.py
radiotools/coreas/generate_coreas_sim.py
radiotools/coreas/geninp_aera.py
radiotools/coreas_selector/generate_events.py
radiotools/coreas_selector/make_event_props_list.py
radiotools/doc/Makefile
radiotools/doc/analyses.rst
radiotools/doc/conf.py
radiotools/doc/coordinatesystems.rst
radiotools/doc/helper.rst
radiotools/doc/index.rst
radiotools/doc/plthelpers.rst
radiotools-0.2.3.dist-info/LICENSE
radiotools-0.2.3.dist-info/WHEEL
radiotools-0.2.3.dist-info/METADATA
radiotools-0.2.3.dist-info/RECORD
