Metadata-Version: 2.1
Name: radiotools
Version: 0.2.3
Summary: A tool package for cosmic-ray and neutrino radio detectors.
Home-page: https://github.com/nu-radio/radiotools
Author: Christian Glaser
Author-email: work@c-glaser.de
Requires-Python: >=3.6
Classifier: License :: OSI Approved :: GNU General Public License v3 or later (GPLv3+)
Requires-Dist: numpy
Requires-Dist: scipy
